prodigyopt/__init__.py
prodigyopt/prodigy.py
prodigyopt-1.1.1.dist-info/LICENSE
prodigyopt-1.1.1.dist-info/METADATA
prodigyopt-1.1.1.dist-info/WHEEL
prodigyopt-1.1.1.dist-info/top_level.txt
prodigyopt-1.1.1.dist-info/RECORD
