Metadata-Version: 2.1
Name: prodigyopt
Version: 1.1.1
Summary: An Adam-like optimizer for neural networks with adaptive estimation of learning rate
Home-page: https://github.com/konstmish/prodigy
Author: Konstantin Mishchenko
Author-email: konsta.mish@gmail.com
Classifier: Programming Language :: Python :: 3
Classifier: License :: OSI Approved :: MIT License
Classifier: Operating System :: OS Independent
Requires-Python: >=3.6
License-File: LICENSE
